greenflowlab/__init__.py
greenflowlab/_frontend.py
greenflowlab/_version.py
greenflowlab/greenflowmodel.py
greenflowlab/handlers.py
greenflowlab/server_utils.py
greenflowlab/labextension/package.json
greenflowlab/labextension/static/216.9c3f657a1ea037792d3e.js
greenflowlab/labextension/static/216.9c3f657a1ea037792d3e.js.LICENSE.txt
greenflowlab/labextension/static/272.2726eab88efa59a99ed3.js
greenflowlab/labextension/static/272.526c30856c7b4e29d761.js
greenflowlab/labextension/static/33.6e7e989ce536d900dd09.js
greenflowlab/labextension/static/33.6e7e989ce536d900dd09.js.LICENSE.txt
greenflowlab/labextension/static/395.e4eb682374fdcd6feabe.js
greenflowlab/labextension/static/44.9906967172a1dc375789.js
greenflowlab/labextension/static/534.39105bcda1b864a7d2c2.js
greenflowlab/labextension/static/534.39105bcda1b864a7d2c2.js.LICENSE.txt
greenflowlab/labextension/static/534.baaf52784501698bbd9f.js
greenflowlab/labextension/static/534.baaf52784501698bbd9f.js.LICENSE.txt
greenflowlab/labextension/static/549.117d2a5eee76f0305d4b.js
greenflowlab/labextension/static/693.a387e0a091bd6f7c0cf3.js
greenflowlab/labextension/static/742.026489f6d0463d896681.js
greenflowlab/labextension/static/788.3ad9e8aeb5a197800739.js
greenflowlab/labextension/static/901.4689892f4ab636937ff4.js
greenflowlab/labextension/static/979.35a85bdc328f8ec61549.js
greenflowlab/labextension/static/979.35a85bdc328f8ec61549.js.LICENSE.txt
greenflowlab/labextension/static/remoteEntry.573ea0f0324f03edc5ab.js
greenflowlab/labextension/static/remoteEntry.c767b1d76ba8f5b1f2ac.js
greenflowlab/labextension/static/style.js
greenflowlab-1.0.5.data/data/etc/jupyter/jupyter_server_config.d/greenflowlab.json
greenflowlab-1.0.5.data/data/share/jupyter/labextensions/greenflowlab/package.json
greenflowlab-1.0.5.data/data/share/jupyter/labextensions/greenflowlab/static/216.9c3f657a1ea037792d3e.js
greenflowlab-1.0.5.data/data/share/jupyter/labextensions/greenflowlab/static/216.9c3f657a1ea037792d3e.js.LICENSE.txt
greenflowlab-1.0.5.dist-info/LICENSE
greenflowlab-1.0.5.dist-info/METADATA
greenflowlab-1.0.5.dist-info/WHEEL
greenflowlab-1.0.5.dist-info/top_level.txt
greenflowlab-1.0.5.dist-info/RECORD
