Metadata-Version: 2.1
Name: greenflowlab
Version: 1.0.5
Summary: greenflow Jupyterlab extension
Home-page: https://github.com/NVIDIA/fsi-samples/tree/main/greenflowlab
Author: {'name': 'Yi Dong', 'email': 'doyend@gmail.com'}
License: Apache
Keywords: Jupyter,JupyterLab,JupyterLab3
Platform: Linux
Platform: Mac OS X
Platform: Windows
Classifier: Programming Language :: Python
Classifier: Programming Language :: Python :: 3
Classifier: Programming Language :: Python :: 3.6
Classifier: Programming Language :: Python :: 3.7
Classifier: Programming Language :: Python :: 3.8
Classifier: Framework :: Jupyter
Requires-Python: >=3.6
Requires-Dist: jupyterlab (==3.*,>=3.0.0rc13)
Requires-Dist: ipywidgets
Requires-Dist: greenflow
